lisien/__init__.py
lisien/android_service.py
lisien/cache.py
lisien/character.py
lisien/collections.py
lisien/db.py
lisien/engine.py
lisien/exc.py
lisien/facade.py
lisien/node.py
lisien/portal.py
lisien/pqdb.py
lisien/py.typed
lisien/query.py
lisien/rule.py
lisien/sql.py
lisien/types.py
lisien/util.py
lisien/window.py
lisien/world.rng
lisien/wrap.py
lisien/examples/__init__.py
lisien/examples/college.py
lisien/examples/export_examples.py
lisien/examples/kobold.py
lisien/examples/pathfind.py
lisien/examples/polygons.py
lisien/examples/sickle.py
lisien/examples/wolfsheep.py
lisien/proxy/__init__.py
lisien/proxy/__main__.py
lisien/proxy/abc.py
lisien/proxy/character.py
lisien/proxy/engine.py
lisien/proxy/handle.py
lisien/proxy/manager.py
lisien/proxy/routine.py
lisien/proxy/worker_subinterpreter.py
lisien/server/__init__.py
lisien/server/__main__.py
lisien/tests/__init__.py
lisien/tests/conftest.py
lisien/tests/regen_test_xml.py
lisien/tests/remake_college24.py
lisien/tests/test_branch_plan.py
lisien/tests/test_character.py
lisien/tests/test_contents.py
lisien/tests/test_delta.py
lisien/tests/test_examples.py
lisien/tests/test_handle.py
lisien/tests/test_import_export.py
lisien/tests/test_load.py
lisien/tests/test_msgpack.py
lisien/tests/test_neighborhood.py
lisien/tests/test_next_turn.py
lisien/tests/test_performance.py
lisien/tests/test_place.py
lisien/tests/test_proxy.py
lisien/tests/test_query.py
lisien/tests/test_resume.py
lisien/tests/test_rule.py
lisien/tests/test_rule_poller.py
lisien/tests/test_storage.py
lisien/tests/test_thing.py
lisien/tests/test_time_travel.py
lisien/tests/test_window.py
lisien/tests/util.py
lisien/tests/data/__init__.py
lisien/tests/data/college24_premade.tar.xz
lisien/tests/data/kobold_0.xml
lisien/tests/data/kobold_1.xml
lisien/tests/data/pathfind.tar.gz
lisien/tests/data/polygons_0.xml
lisien/tests/data/polygons_1.xml
lisien/tests/data/wolfsheep_0.xml
lisien/tests/data/wolfsheep_1.xml
lisien-0.23.1.dist-info/licenses/LICENSE
lisien-0.23.1.dist-info/METADATA
lisien-0.23.1.dist-info/WHEEL
lisien-0.23.1.dist-info/top_level.txt
lisien-0.23.1.dist-info/RECORD
