Metadata-Version: 2.4
Name: lisien
Version: 0.23.1
Summary: Life Simulator Engine
Author-email: Zachary Spector <public@zacharyspector.com>
License-Expression: AGPL-3.0-only
Project-URL: Homepage, https://codeberg.org/clayote/Lisien
Project-URL: Bug Tracker, https://codeberg.org/clayote/Lisien/issues
Classifier: Programming Language :: Python :: 3
Classifier: Operating System :: OS Independent
Classifier: Topic :: Software Development :: Libraries
Classifier: Intended Audience :: Developers
Classifier: Development Status :: 3 - Alpha
Requires-Python: ~=3.12
License-File: LICENSE
Requires-Dist: reslot~=0.10
Requires-Dist: blinker~=1.4
Requires-Dist: msgpack~=1.1.0
Requires-Dist: u-msgpack-python~=2.8.0
Requires-Dist: networkx~=3.5
Requires-Dist: sqlalchemy~=2.0
Requires-Dist: numpy~=2.3.4
Requires-Dist: tblib~=3.2.0
Requires-Dist: parquetdb
Requires-Dist: annotated-types~=0.7.0
Requires-Dist: lxml~=6.0
Dynamic: license-file
